binhopulsar/__init__.py
binhopulsar/pulsar.py
binhopulsar/commands/__init__.py
binhopulsar/commands/gpio/__init__.py
binhopulsar/commands/gpio/definitions.py
binhopulsar/commands/i2c/__init__.py
binhopulsar/commands/i2c/definitions.py
binhopulsar/commands/spi/__init__.py
binhopulsar/commands/spi/definitions.py
binhopulsar/commands/system/__init__.py
binhopulsar/commands/system/definitions.py
binhopulsar/commands/uart/__init__.py
binhopulsar/commands/uart/definitions.py
binhopulsar/supernovasdk/binhosupernova/__init__.py
binhopulsar/supernovasdk/binhosupernova/supernova.py
binhopulsar/supernovasdk/binhosupernova/commands/__init__.py
binhopulsar/supernovasdk/binhosupernova/commands/common_definitions.py
binhopulsar/supernovasdk/binhosupernova/commands/gpio/__init__.py
binhopulsar/supernovasdk/binhosupernova/commands/gpio/definitions.py
binhopulsar/supernovasdk/binhosupernova/commands/gpio/serializers.py
binhopulsar/supernovasdk/binhosupernova/commands/gpio/validators.py
binhopulsar/supernovasdk/binhosupernova/commands/helpers/__init__.py
binhopulsar/supernovasdk/binhosupernova/commands/helpers/validator.py
binhopulsar/supernovasdk/binhosupernova/commands/i2c/__init__.py
binhopulsar/supernovasdk/binhosupernova/commands/i2c/definitions.py
binhopulsar/supernovasdk/binhosupernova/commands/i2c/serializers.py
binhopulsar/supernovasdk/binhosupernova/commands/i2c/validators.py
binhopulsar/supernovasdk/binhosupernova/commands/i3c/__init__.py
binhopulsar/supernovasdk/binhosupernova/commands/i3c/definitions.py
binhopulsar/supernovasdk/binhosupernova/commands/i3c/serializers.py
binhopulsar/supernovasdk/binhosupernova/commands/i3c/validators.py
binhopulsar/supernovasdk/binhosupernova/commands/spi/__init__.py
binhopulsar/supernovasdk/binhosupernova/commands/spi/definitions.py
binhopulsar/supernovasdk/binhosupernova/commands/spi/serializers.py
binhopulsar/supernovasdk/binhosupernova/commands/spi/validators.py
binhopulsar/supernovasdk/binhosupernova/commands/system/__init__.py
binhopulsar-1.2.0.dist-info/METADATA
binhopulsar-1.2.0.dist-info/WHEEL
binhopulsar-1.2.0.dist-info/top_level.txt
binhopulsar-1.2.0.dist-info/RECORD
