Metadata-Version: 2.1
Name: binhopulsar
Version: 1.2.0
Summary: Basic SDK for Binho Pulsar
Home-page: https://github.com/binhollc/PulsarSDK
Author: Binho LLC
Author-email: support@binho.io
License: Private
Classifier: Development Status :: 3 - Alpha
Classifier: Intended Audience :: Developers
Classifier: Programming Language :: Python :: 3
Classifier: Operating System :: OS Independent
Requires-Python: >=3.8
Requires-Dist: pyserial
Requires-Dist: hidapi
Requires-Dist: psutil
